bireyselvalue/__init__.py
bireyselvalue/bireyselvalue.py
bireyselvalue-2.1.0.dist-info/LICENSE.txt
bireyselvalue-2.1.0.dist-info/METADATA
bireyselvalue-2.1.0.dist-info/WHEEL
bireyselvalue-2.1.0.dist-info/top_level.txt
bireyselvalue-2.1.0.dist-info/RECORD
