Metadata-Version: 2.1
Name: bireyselvalue
Version: 2.1.0
Summary: TEST ON V.1 of THE BireyselValue Algorithm FOR CLASSIFICATION PROBLEMS
Home-page: https://github.com/dahmansphi/bireyselvalue_v1
Author: Dr. Deniz Dahman's
Author-email: dahmansphi@gmail.com
Keywords: classification,bireyselvalue,machine learning
Classifier: Development Status :: 3 - Alpha
Classifier: Intended Audience :: Developers
Classifier: Topic :: Software Development :: Build Tools
Classifier: License :: OSI Approved :: MIT License
Classifier: Programming Language :: Python :: 3
Requires-Python: >=3.9
License-File: LICENSE.txt
